LICENSE
MANIFEST.in
README.rst
VERSION
requirements.txt
setup.py
src/cdumay_opentracing/__init__.py
src/cdumay_opentracing.egg-info/PKG-INFO
src/cdumay_opentracing.egg-info/SOURCES.txt
src/cdumay_opentracing.egg-info/dependency_links.txt
src/cdumay_opentracing.egg-info/requires.txt
src/cdumay_opentracing.egg-info/top_level.txt
src/cdumay_opentracing.egg-info/zip-safe