Metadata-Version: 2.1
Name: cdumay-opentracing
Version: 0.1.3
Summary: Library to facilitate opentracing integration
Home-page: https://github.com/cdumay/cdumay-opentracing
Author: Cedric DUMAY
Author-email: cedric.dumay@gmail.com
License: MIT
Platform: UNKNOWN
Classifier: Programming Language :: Python
Provides-Extra: flask
